tracardi_inject_event/plugin.py
tracardi_inject_event/model/configuration.py
tracardi_inject_event/model/__pycache__/configuration.cpython-38.pyc
tracardi_inject_event/test/manual_test.py
tracardi_inject_event-0.3.dist-info/LICENSE.md
tracardi_inject_event-0.3.dist-info/METADATA
tracardi_inject_event-0.3.dist-info/WHEEL
tracardi_inject_event-0.3.dist-info/top_level.txt
tracardi_inject_event-0.3.dist-info/RECORD
